{"current_elo":2113.0,"elo_history":[{"elo":2031.0,"record_id":"tb8PHN1U","session_id":"tmCET3UJ","timestamp_ms":1766758342721},{"elo":2031.0,"record_id":"38B4gq8o","session_id":"tmCET3UJ","timestamp_ms":1766758531380},{"elo":2031.0,"record_id":"DKLqGnu2","session_id":"tmCET3UJ","timestamp_ms":1766758729743},{"elo":2031.0,"record_id":"iwdy1pZj","session_id":"tmCET3UJ","timestamp_ms":1766758854591},{"elo":2031.0,"record_id":"4kGm7Xpu","session_id":"tmCET3UJ","timestamp_ms":1766759037912},{"elo":2031.0,"record_id":"9c78GNPX","session_id":"tmCET3UJ","timestamp_ms":1766759185200},{"elo":2031.0,"record_id":"Ue1mTe8M","session_id":"tmCET3UJ","timestamp_ms":1766759317238},{"elo":2031.0,"record_id":"wdLLNZ6P","session_id":"tmCET3UJ","timestamp_ms":1766759484193},{"elo":2031.0,"record_id":"fk9ZPnvk","session_id":"tmCET3UJ","timestamp_ms":1766759681978},{"elo":2031.0,"record_id":"Ny7q0DDq","session_id":"tmCET3UJ","timestamp_ms":1766759816403},{"elo":2031.0,"record_id":"qiBLyJ1t","session_id":"tmCET3UJ","timestamp_ms":1766759983005},{"elo":2031.0,"record_id":"wvScoemf","session_id":"tmCET3UJ","timestamp_ms":1766760155313},{"elo":2031.0,"record_id":"XBWyvSJH","session_id":"tmCET3UJ","timestamp_ms":1766760308853},{"elo":2031.0,"record_id":"FJEA6aVp","session_id":"tmCET3UJ","timestamp_ms":1766760401989},{"elo":2031.0,"record_id":"2Xk3JqfN","session_id":"tmCET3UJ","timestamp_ms":1766760582035},{"elo":2031.0,"record_id":"MJzb4rqj","session_id":"tmCET3UJ","timestamp_ms":1766760859405},{"elo":2066.0,"record_id":"aeU9PsmW","session_id":"jtwGXUNg","timestamp_ms":1766761329364},{"elo":2066.0,"record_id":"fXwei5H1","session_id":"jtwGXUNg","timestamp_ms":1766761452039},{"elo":2066.0,"record_id":"FfCjXoM0","session_id":"jtwGXUNg","timestamp_ms":1766761604756},{"elo":2066.0,"record_id":"qVySGbP9","session_id":"jtwGXUNg","timestamp_ms":1766761739265},{"elo":2066.0,"record_id":"YjLiynRH","session_id":"jtwGXUNg","timestamp_ms":1766761976295},{"elo":2066.0,"record_id":"42jghic6","session_id":"jtwGXUNg","timestamp_ms":1766762150019},{"elo":2066.0,"record_id":"ciyHEsiR","session_id":"jtwGXUNg","timestamp_ms":1766762379903},{"elo":2066.0,"record_id":"T3SnWLLL","session_id":"jtwGXUNg","timestamp_ms":1766762481564},{"elo":2066.0,"record_id":"SQfbY3MW","session_id":"jtwGXUNg","timestamp_ms":1766762679829},{"elo":2066.0,"record_id":"s8bFoxFT","session_id":"jtwGXUNg","timestamp_ms":1766762810960},{"elo":2066.0,"record_id":"9ddsqJgf","session_id":"jtwGXUNg","timestamp_ms":1766762946852},{"elo":2066.0,"record_id":"Gje4xDS2","session_id":"jtwGXUNg","timestamp_ms":1766763194725},{"elo":2066.0,"record_id":"bmYi8VKY","session_id":"jtwGXUNg","timestamp_ms":1766763390976},{"elo":2066.0,"record_id":"oVxFy4X9","session_id":"jtwGXUNg","timestamp_ms":1766763563869},{"elo":2066.0,"record_id":"94SQQEuc","session_id":"jtwGXUNg","timestamp_ms":1766763712588},{"elo":2066.0,"record_id":"prNB2GRE","session_id":"jtwGXUNg","timestamp_ms":1766763901758},{"elo":2052.0,"record_id":"CdtUNGcX","session_id":"UjrBYvbv","timestamp_ms":1767277138321},{"elo":2052.0,"record_id":"tPhBTcra","session_id":"UjrBYvbv","timestamp_ms":1767277286192},{"elo":2052.0,"record_id":"UYbPShim","session_id":"UjrBYvbv","timestamp_ms":1767277431480},{"elo":2052.0,"record_id":"7q6LLCuK","session_id":"UjrBYvbv","timestamp_ms":1767277583108},{"elo":2052.0,"record_id":"Nf4WVyv1","session_id":"UjrBYvbv","timestamp_ms":1767277793166},{"elo":2052.0,"record_id":"YrEG5wMu","session_id":"UjrBYvbv","timestamp_ms":1767278048098},{"elo":2052.0,"record_id":"8ycNkjKK","session_id":"UjrBYvbv","timestamp_ms":1767278206909},{"elo":2052.0,"record_id":"0B1kibe1","session_id":"UjrBYvbv","timestamp_ms":1767278306597},{"elo":2052.0,"record_id":"C8TGp4hz","session_id":"UjrBYvbv","timestamp_ms":1767278435397},{"elo":2052.0,"record_id":"csNx4zBe","session_id":"UjrBYvbv","timestamp_ms":1767278608115},{"elo":2052.0,"record_id":"etWon9MM","session_id":"UjrBYvbv","timestamp_ms":1767278724359},{"elo":2052.0,"record_id":"jkMAw04f","session_id":"UjrBYvbv","timestamp_ms":1767278824526},{"elo":2052.0,"record_id":"MEnJRfrm","session_id":"UjrBYvbv","timestamp_ms":1767278944320},{"elo":2052.0,"record_id":"4UZcvRyy","session_id":"UjrBYvbv","timestamp_ms":1767279166700},{"elo":2052.0,"record_id":"tBNGKWcJ","session_id":"UjrBYvbv","timestamp_ms":1767279377398},{"elo":2052.0,"record_id":"2ke35mNR","session_id":"UjrBYvbv","timestamp_ms":1767279534103},{"elo":2084.0,"record_id":"PCbSdq6G","session_id":"7ERLgJui","timestamp_ms":1767448795898},{"elo":2084.0,"record_id":"bA1yjJJv","session_id":"7ERLgJui","timestamp_ms":1767448980207},{"elo":2084.0,"record_id":"KGL87sRN","session_id":"7ERLgJui","timestamp_ms":1767449118903},{"elo":2084.0,"record_id":"ATDQmT7f","session_id":"7ERLgJui","timestamp_ms":1767449261932},{"elo":2084.0,"record_id":"iGkDz0Q1","session_id":"7ERLgJui","timestamp_ms":1767449467468},{"elo":2084.0,"record_id":"Bc8Su349","session_id":"7ERLgJui","timestamp_ms":1767449592339},{"elo":2084.0,"record_id":"GTyq2tV6","session_id":"7ERLgJui","timestamp_ms":1767449765468},{"elo":2084.0,"record_id":"fW133N5X","session_id":"7ERLgJui","timestamp_ms":1767449888958},{"elo":2084.0,"record_id":"ibUdZU9r","session_id":"7ERLgJui","timestamp_ms":1767450182017},{"elo":2084.0,"record_id":"pojuPpJv","session_id":"7ERLgJui","timestamp_ms":1767450380038},{"elo":2084.0,"record_id":"uUaTDiVA","session_id":"7ERLgJui","timestamp_ms":1767450553158},{"elo":2084.0,"record_id":"CqKqC0c7","session_id":"7ERLgJui","timestamp_ms":1767450701411},{"elo":2084.0,"record_id":"41D6qbE4","session_id":"7ERLgJui","timestamp_ms":1767450773433},{"elo":2084.0,"record_id":"P1VcsWCS","session_id":"7ERLgJui","timestamp_ms":1767450989610},{"elo":2084.0,"record_id":"ayw8xyz3","session_id":"7ERLgJui","timestamp_ms":1767451208597},{"elo":2084.0,"record_id":"39JKJ2Eq","session_id":"7ERLgJui","timestamp_ms":1767451331660},{"elo":2113.0,"record_id":"AEuVdM24","session_id":"LUWWHGjR","timestamp_ms":1767451580238},{"elo":2113.0,"record_id":"UcurE5Uz","session_id":"LUWWHGjR","timestamp_ms":1767451742761},{"elo":2113.0,"record_id":"BrH7wGfo","session_id":"LUWWHGjR","timestamp_ms":1767451905128},{"elo":2113.0,"record_id":"8kiYfe09","session_id":"LUWWHGjR","timestamp_ms":1767452179593},{"elo":2113.0,"record_id":"JwtJFbbi","session_id":"LUWWHGjR","timestamp_ms":1767452313772},{"elo":2113.0,"record_id":"XkicjAiJ","session_id":"LUWWHGjR","timestamp_ms":1767452525741},{"elo":2113.0,"record_id":"hwtNK8Js","session_id":"LUWWHGjR","timestamp_ms":1767452715142},{"elo":2113.0,"record_id":"QzFrPDBi","session_id":"LUWWHGjR","timestamp_ms":1767452820472},{"elo":2113.0,"record_id":"ppSaNaFV","session_id":"LUWWHGjR","timestamp_ms":1767452964188},{"elo":2113.0,"record_id":"uhv4gmSu","session_id":"LUWWHGjR","timestamp_ms":1767453131183},{"elo":2113.0,"record_id":"D44USegf","session_id":"LUWWHGjR","timestamp_ms":1767453318049},{"elo":2113.0,"record_id":"0EqAG19f","session_id":"LUWWHGjR","timestamp_ms":1767453382853},{"elo":2113.0,"record_id":"CCFhMV4x","session_id":"LUWWHGjR","timestamp_ms":1767453470935},{"elo":2113.0,"record_id":"w4s5n4qn","session_id":"LUWWHGjR","timestamp_ms":1767453654328},{"elo":2113.0,"record_id":"3P8z04dZ","session_id":"LUWWHGjR","timestamp_ms":1767453750322},{"elo":2113.0,"record_id":"TFfrttMx","session_id":"LUWWHGjR","timestamp_ms":1767453859428}],"name":"章无律","player_id":"8Nxy9k2G","processed_records":["tb8PHN1U","38B4gq8o","DKLqGnu2","iwdy1pZj","4kGm7Xpu","9c78GNPX","Ue1mTe8M","wdLLNZ6P","fk9ZPnvk","Ny7q0DDq","qiBLyJ1t","wvScoemf","XBWyvSJH","FJEA6aVp","2Xk3JqfN","MJzb4rqj","aeU9PsmW","fXwei5H1","FfCjXoM0","qVySGbP9","YjLiynRH","42jghic6","ciyHEsiR","T3SnWLLL","SQfbY3MW","s8bFoxFT","9ddsqJgf","Gje4xDS2","bmYi8VKY","oVxFy4X9","94SQQEuc","prNB2GRE","CdtUNGcX","tPhBTcra","UYbPShim","7q6LLCuK","Nf4WVyv1","YrEG5wMu","8ycNkjKK","0B1kibe1","C8TGp4hz","csNx4zBe","etWon9MM","jkMAw04f","MEnJRfrm","4UZcvRyy","tBNGKWcJ","2ke35mNR","PCbSdq6G","bA1yjJJv","KGL87sRN","ATDQmT7f","iGkDz0Q1","Bc8Su349","GTyq2tV6","fW133N5X","ibUdZU9r","pojuPpJv","uUaTDiVA","CqKqC0c7","41D6qbE4","P1VcsWCS","ayw8xyz3","39JKJ2Eq","AEuVdM24","UcurE5Uz","BrH7wGfo","8kiYfe09","JwtJFbbi","XkicjAiJ","hwtNK8Js","QzFrPDBi","ppSaNaFV","uhv4gmSu","D44USegf","0EqAG19f","CCFhMV4x","w4s5n4qn","3P8z04dZ","TFfrttMx"],"processed_sessions":["LUWWHGjR","UjrBYvbv","jtwGXUNg","tmCET3UJ","7ERLgJui"],"stats":{"average_step_seconds":1.3159279826464203,"deal_in_count":14,"draw_count":1,"ron_win_count":18,"sessions_recorded":5,"total_rounds":80,"total_session_seconds":3033.213999999999,"total_steps":2305,"tsumo_against_count":15,"tsumo_win_count":5,"win_count":23},"wins":[{"hand_raw":"[PPP,2]789m12pCCFFF3p|EE0000","max_fans":[{"count":1,"name":"小三元","points":64}],"record_id":"38B4gq8o","session_id":"tmCET3UJ","timestamp_ms":1766758531380,"total_fan":71,"win_type":"ron"},{"hand_raw":"456m89p12355567s7p|WS1000","max_fans":[{"count":1,"name":"花龙","points":8}],"record_id":"Ny7q0DDq","session_id":"tmCET3UJ","timestamp_ms":1766759816403,"total_fan":17,"win_type":"tsumo"},{"hand_raw":"[123m,3][789m,3]11456p79s8s|WE0000","max_fans":[{"count":1,"name":"花龙","points":8}],"record_id":"qiBLyJ1t","session_id":"tmCET3UJ","timestamp_ms":1766759983005,"total_fan":13,"win_type":"ron"},{"hand_raw":"[PPP,3]2345566699m5m|NS1000","max_fans":[{"count":1,"name":"混一色","points":6}],"record_id":"2Xk3JqfN","session_id":"tmCET3UJ","timestamp_ms":1766760582035,"total_fan":14,"win_type":"tsumo"},{"hand_raw":"[345p,3]567m1299p456s3p|NE1000","max_fans":[{"count":1,"name":"三色三步高","points":6}],"record_id":"MJzb4rqj","session_id":"tmCET3UJ","timestamp_ms":1766760859405,"total_fan":12,"win_type":"tsumo"},{"hand_raw":"[567s,1]12334567m77p5m|EN0000","max_fans":[{"count":1,"name":"一色三连环","points":16}],"record_id":"fXwei5H1","session_id":"jtwGXUNg","timestamp_ms":1766761452039,"total_fan":20,"win_type":"ron"},{"hand_raw":"[9999p,5][111p,2][PPP,2]77pFFF|ES0000","max_fans":[{"count":1,"name":"碰碰和","points":6},{"count":1,"name":"混一色","points":6},{"count":1,"name":"双箭刻","points":6}],"record_id":"qVySGbP9","session_id":"jtwGXUNg","timestamp_ms":1766761739265,"total_fan":24,"win_type":"ron"},{"hand_raw":"[345s,3][999s,2]6677888s8s|WS0000","max_fans":[{"count":1,"name":"清一色","points":24}],"record_id":"9ddsqJgf","session_id":"jtwGXUNg","timestamp_ms":1766762946852,"total_fan":34,"win_type":"ron"},{"hand_raw":"456m789p1234467s5s|EW0000","max_fans":[{"count":1,"name":"花龙","points":8}],"record_id":"tPhBTcra","session_id":"UjrBYvbv","timestamp_ms":1767277286192,"total_fan":13,"win_type":"ron"},{"hand_raw":"[888m,2][888s,2]666p3455s2s|SW0100","max_fans":[{"count":1,"name":"和绝张","points":4}],"record_id":"Nf4WVyv1","session_id":"UjrBYvbv","timestamp_ms":1767277793166,"total_fan":10,"win_type":"ron"},{"hand_raw":"[FFF,1]123m45p789sNN6p|SS0000","max_fans":[{"count":1,"name":"花龙","points":8}],"record_id":"YrEG5wMu","session_id":"UjrBYvbv","timestamp_ms":1767278048098,"total_fan":18,"win_type":"ron"},{"hand_raw":"[NNNN,6][555m,1][333m,3]999mWW|WS1000","max_fans":[{"count":1,"name":"碰碰和","points":6},{"count":1,"name":"混一色","points":6}],"record_id":"C8TGp4hz","session_id":"UjrBYvbv","timestamp_ms":1767278435397,"total_fan":18,"win_type":"tsumo"},{"hand_raw":"[EEE,3]12m789p456sFF3m|WE0000","max_fans":[{"count":1,"name":"花龙","points":8}],"record_id":"csNx4zBe","session_id":"UjrBYvbv","timestamp_ms":1767278608115,"total_fan":18,"win_type":"ron"},{"hand_raw":"25m147p69sESWNFPC|NN0000","max_fans":[{"count":1,"name":"七星不靠","points":24}],"record_id":"4UZcvRyy","session_id":"UjrBYvbv","timestamp_ms":1767279166700,"total_fan":27,"win_type":"ron"},{"hand_raw":"123m2488p345sSSS3p|ES0000","max_fans":[{"count":1,"name":"三色三步高","points":6}],"record_id":"PCbSdq6G","session_id":"7ERLgJui","timestamp_ms":1767448795898,"total_fan":13,"win_type":"ron"},{"hand_raw":"[FFFF,1][777m,1][999m,1]1166m1m|EE0000","max_fans":[{"count":1,"name":"碰碰和","points":6},{"count":1,"name":"混一色","points":6}],"record_id":"bA1yjJJv","session_id":"7ERLgJui","timestamp_ms":1767448980207,"total_fan":19,"win_type":"ron"},{"hand_raw":"[567m,2]11678p34579s8s|EN0000","max_fans":[{"count":1,"name":"三色三步高","points":6}],"record_id":"KGL87sRN","session_id":"7ERLgJui","timestamp_ms":1767449118903,"total_fan":9,"win_type":"ron"},{"hand_raw":"[123m,1][456s,1]34567m22s5m|SW0000","max_fans":[{"count":1,"name":"一色三连环","points":16}],"record_id":"GTyq2tV6","session_id":"7ERLgJui","timestamp_ms":1767449765468,"total_fan":22,"win_type":"ron"},{"hand_raw":"[WWW,3][FFF,2][123p,2]678m1s1s|WW0000","max_fans":[{"count":1,"name":"五门齐","points":6}],"record_id":"ibUdZU9r","session_id":"7ERLgJui","timestamp_ms":1767450182017,"total_fan":13,"win_type":"ron"},{"hand_raw":"[789p,1]11456m12346p5p|WE0000","max_fans":[{"count":1,"name":"清龙","points":16}],"record_id":"uUaTDiVA","session_id":"7ERLgJui","timestamp_ms":1767450553158,"total_fan":24,"win_type":"ron"},{"hand_raw":"[123p,2]12346m66p123s5m|SN0000","max_fans":[{"count":1,"name":"三色三同顺","points":8}],"record_id":"hwtNK8Js","session_id":"LUWWHGjR","timestamp_ms":1767452715142,"total_fan":13,"win_type":"ron"},{"hand_raw":"[222s,3]45m34566p567s6m|NW1000","max_fans":[{"count":1,"name":"三色三步高","points":6}],"record_id":"CCFhMV4x","session_id":"LUWWHGjR","timestamp_ms":1767453470935,"total_fan":10,"win_type":"tsumo"},{"hand_raw":"[345p,2]12356m23488s4m|NS0000","max_fans":[{"count":1,"name":"三色三步高","points":6}],"record_id":"w4s5n4qn","session_id":"LUWWHGjR","timestamp_ms":1767453654328,"total_fan":9,"win_type":"ron"}]}