{"alias_history":[{"first_seen_ts":1745585198405,"last_seen_ts":1746623330855,"name":"玉逍遥"}],"current_elo":2111.0,"elo_history":[{"elo":2080.0,"session_id":"CjkZLwB5","timestamp_ms":1745588959729},{"elo":2093.0,"session_id":"N5wJi1Lt","timestamp_ms":1745645206768},{"elo":2123.0,"session_id":"v6y0sB6C","timestamp_ms":1745649198331},{"elo":2154.0,"session_id":"Fcgs3nrU","timestamp_ms":1745666969069},{"elo":2141.0,"session_id":"vSpUgAkP","timestamp_ms":1745670234806},{"elo":2111.0,"session_id":"fHmHb7VG","timestamp_ms":1746623330855}],"last_elo_ts":1746623330855,"name":"玉逍遥","player_id":"EuEENGBJ","processed_sessions":["v6y0sB6C","CjkZLwB5","vSpUgAkP","N5wJi1Lt","Fcgs3nrU","fHmHb7VG"],"stats":{"average_step_seconds":1.18537378954164,"avg_starting_shanten_13":3.9027777777777777,"avg_starting_shanten_14":3.4583333333333335,"deal_in_count":15,"draw_count":3,"ron_win_count":27,"sessions_recorded":6,"shanten_distribution_13":{"2":7,"3":20,"4":25,"5":13,"6":7},"shanten_distribution_14":{"1":1,"3":12,"4":9,"5":2},"starting_shanten_count_13":72,"starting_shanten_count_14":24,"total_rounds":96,"total_session_seconds":3672.288000000001,"total_starting_shanten_13":281,"total_starting_shanten_14":83,"total_steps":3098,"tsumo_against_count":20,"tsumo_win_count":5,"win_count":32},"wins":[{"hand_raw":"[111s,2]34556779sPP8s|EW0000","max_fans":[{"count":1,"name":"一色三连环","points":16}],"record_id":"3TJ8Yoxm","session_id":"CjkZLwB5","starting_hand_raw":"4m115779sEWNCFP|EW0000","timestamp_ms":1745585733908,"total_fan":24,"win_type":"ron"},{"hand_raw":"[789p,3]34678m11567s2m|ES0000","max_fans":[{"count":1,"name":"三色三步高","points":6}],"record_id":"mU5kBP8Q","session_id":"CjkZLwB5","starting_hand_raw":"168m1679p126sEWN|ES0000","timestamp_ms":1745585995585,"total_fan":10,"win_type":"ron"},{"hand_raw":"[789s,1][789p,2][345m,2]79m22p8m|SS0000","max_fans":[{"count":1,"name":"三色三同顺","points":8}],"record_id":"9h5X67TA","session_id":"CjkZLwB5","starting_hand_raw":"357m22779p39sWWC|SS0000","timestamp_ms":1745586309724,"total_fan":14,"win_type":"ron"},{"hand_raw":"[123m,2][EEE,3]789p567sFF|SN0000","max_fans":[{"count":1,"name":"五门齐","points":6}],"record_id":"reZV5d1T","session_id":"CjkZLwB5","starting_hand_raw":"1m1789p5679sEENF|SN0000","timestamp_ms":1745586895883,"total_fan":8,"win_type":"ron"},{"hand_raw":"34599m234789p12s3s|WW0000","max_fans":[{"count":1,"name":"三色三步高","points":6}],"record_id":"f36W2f30","session_id":"CjkZLwB5","starting_hand_raw":"4599m123477p122s|WW0000","timestamp_ms":1745587552952,"total_fan":15,"win_type":"ron"},{"hand_raw":"123m45p567sEEECC3p|NE0000","max_fans":[{"count":1,"name":"五门齐","points":6}],"record_id":"kyyBpMCJ","session_id":"CjkZLwB5","starting_hand_raw":"122358m1p556sENCP|NE0000","timestamp_ms":1745588720329,"total_fan":10,"win_type":"ron"},{"hand_raw":"3368m567p345789s7m|EW0000","max_fans":[{"count":1,"name":"三色三步高","points":6}],"record_id":"MtHCJe7K","session_id":"N5wJi1Lt","starting_hand_raw":"338m567p34778sCF|EW0000","timestamp_ms":1745642611971,"total_fan":13,"win_type":"ron"},{"hand_raw":"[PPP,2][999s,3]345m234pEE|ES1000","max_fans":[{"count":1,"name":"五门齐","points":6}],"record_id":"mjH0a1MT","session_id":"N5wJi1Lt","starting_hand_raw":"124m1249p29sEFPP|ES0000","timestamp_ms":1745642769487,"total_fan":12,"win_type":"tsumo"},{"hand_raw":"[FFF,2][NNN,1]345m23p55s4p|EE0000","max_fans":[{"count":1,"name":"五门齐","points":6}],"record_id":"Y4SybTH4","session_id":"N5wJi1Lt","starting_hand_raw":"135m239p558sSNNFF|EE0000","timestamp_ms":1745642993726,"total_fan":10,"win_type":"ron"},{"hand_raw":"[456m,2]33789m345p67s5s|SE0000","max_fans":[{"count":1,"name":"三色三步高","points":6}],"record_id":"8Ce88auw","session_id":"N5wJi1Lt","starting_hand_raw":"336789m135p677sWP|SE0000","timestamp_ms":1745643339015,"total_fan":13,"win_type":"ron"},{"hand_raw":"234m678p2345567s5s|SN0000","max_fans":[{"count":1,"name":"门前清","points":2},{"count":1,"name":"平和","points":2},{"count":1,"name":"断幺","points":2}],"record_id":"4ExjkkSB","session_id":"N5wJi1Lt","starting_hand_raw":"3m4678p23455sSNF|SN0000","timestamp_ms":1745643529054,"total_fan":9,"win_type":"ron"},{"hand_raw":"[234p,2][567p,1]11345m23s1s|WS0000","max_fans":[{"count":1,"name":"三色三步高","points":6}],"record_id":"w4s4SayM","session_id":"N5wJi1Lt","starting_hand_raw":"1359m24679p239sC|WS0000","timestamp_ms":1745643683574,"total_fan":10,"win_type":"ron"},{"hand_raw":"[999s,2][1111m,6]3388m111p3m|WW0000","max_fans":[{"count":1,"name":"碰碰和","points":6}],"record_id":"AUk7zuYN","session_id":"N5wJi1Lt","starting_hand_raw":"11348m11p2499sEW|WW0000","timestamp_ms":1745644397998,"total_fan":15,"win_type":"ron"},{"hand_raw":"[WWW,3][555s,3][NNN,2]44p22s4p|EN0000","max_fans":[{"count":1,"name":"碰碰和","points":6}],"record_id":"nQW07rGK","session_id":"v6y0sB6C","starting_hand_raw":"478m344p255sWWNN|EN0000","timestamp_ms":1745646604705,"total_fan":11,"win_type":"ron"},{"hand_raw":"[567m,1]33m67p456789s8p|EW0000","max_fans":[{"count":1,"name":"三色三步高","points":6}],"record_id":"gfDijU0R","session_id":"v6y0sB6C","starting_hand_raw":"3347m6p157789sWP|EW0000","timestamp_ms":1745646789132,"total_fan":10,"win_type":"ron"},{"hand_raw":"789m456p23555sCC1s|ES0000","max_fans":[{"count":1,"name":"花龙","points":8}],"record_id":"0uR1KyN9","session_id":"v6y0sB6C","starting_hand_raw":"578m567p3559sWCC|ES0000","timestamp_ms":1745646982970,"total_fan":13,"win_type":"ron"},{"hand_raw":"23468m789p33567s7m|EE0000","max_fans":[{"count":1,"name":"三色三步高","points":6}],"record_id":"GnbphRa5","session_id":"v6y0sB6C","starting_hand_raw":"23468m789p337sNNP|EE0000","timestamp_ms":1745647187190,"total_fan":14,"win_type":"ron"},{"hand_raw":"[789s,2][EEE,3]1233377s7s|WE0000","max_fans":[{"count":1,"name":"混一色","points":6}],"record_id":"tdnM80oq","session_id":"v6y0sB6C","starting_hand_raw":"26m13357779sEESF|WE0000","timestamp_ms":1745648002173,"total_fan":12,"win_type":"ron"},{"hand_raw":"11789p12345678s9s|WW0000","max_fans":[{"count":1,"name":"清龙","points":16}],"record_id":"W91YCquk","session_id":"v6y0sB6C","starting_hand_raw":"4m15889p157sSNCF|WW0000","timestamp_ms":1745648375097,"total_fan":22,"win_type":"ron"},{"hand_raw":"[999s,2]567m11567p56s7s|NS0000","max_fans":[{"count":1,"name":"三色三同顺","points":8}],"record_id":"Ra53sq1J","session_id":"v6y0sB6C","starting_hand_raw":"11257p56699sCFP|NS0000","timestamp_ms":1745649198331,"total_fan":14,"win_type":"ron"},{"hand_raw":"[789s,1]1236678m456p6m|SW0000","max_fans":[{"count":1,"name":"花龙","points":8}],"record_id":"H4wzX8gB","session_id":"Fcgs3nrU","starting_hand_raw":"2678m1458p29sESN|SW0000","timestamp_ms":1745664624112,"total_fan":10,"win_type":"ron"},{"hand_raw":"89m45699p123678s7m|SS0000","max_fans":[{"count":1,"name":"花龙","points":8}],"record_id":"pvgu6Syt","session_id":"Fcgs3nrU","starting_hand_raw":"89m145699p1278sW|SS0000","timestamp_ms":1745664830561,"total_fan":13,"win_type":"ron"},{"hand_raw":"[567m,3]45567p11678s6p|WS0000","max_fans":[{"count":1,"name":"三色三步高","points":6}],"record_id":"T7F5BWfY","session_id":"Fcgs3nrU","starting_hand_raw":"1566m1556p16789s|WS0000","timestamp_ms":1745666032288,"total_fan":10,"win_type":"ron"},{"hand_raw":"[PPP,3][666m,2]55m22sWWW5m|NW1000","max_fans":[{"count":1,"name":"碰碰和","points":6}],"record_id":"u1ivSCmH","session_id":"Fcgs3nrU","starting_hand_raw":"5679m2257sWWWFP|NW0000","timestamp_ms":1745666969069,"total_fan":15,"win_type":"tsumo"},{"hand_raw":"[111m,3][123p,2]44m444p12s3s|ES0000","max_fans":[{"count":1,"name":"小于五","points":12}],"record_id":"8RbyzWuG","session_id":"vSpUgAkP","starting_hand_raw":"11479m134p124sWN|ES0000","timestamp_ms":1745667690725,"total_fan":16,"win_type":"ron"},{"hand_raw":"2278m344556p567s6m|WS0000","max_fans":[{"count":1,"name":"三色三步高","points":6}],"record_id":"R4aiwUz8","session_id":"vSpUgAkP","starting_hand_raw":"229m344559p25sNC|WS0000","timestamp_ms":1745668810605,"total_fan":13,"win_type":"ron"},{"hand_raw":"[CCC,1]123m345p2466s3s|WE0000","max_fans":[{"count":1,"name":"三色三步高","points":6}],"record_id":"pwPa5Bti","session_id":"vSpUgAkP","starting_hand_raw":"1138m599p24668sCC|WE0000","timestamp_ms":1745668923290,"total_fan":9,"win_type":"ron"},{"hand_raw":"[PPP,3]56m234p345sNN7m|SW1000","max_fans":[{"count":1,"name":"五门齐","points":6}],"record_id":"Vr30vAY0","session_id":"fHmHb7VG","starting_hand_raw":"156m234p359sENPP|SW0000","timestamp_ms":1746621185555,"total_fan":11,"win_type":"tsumo"},{"hand_raw":"[888p,1]55599p555sSSS|SE1000","max_fans":[{"count":1,"name":"三暗刻","points":16}],"record_id":"FJB7AWdc","session_id":"fHmHb7VG","starting_hand_raw":"134m55889p159sSSN|SE0000","timestamp_ms":1746621500845,"total_fan":28,"win_type":"tsumo"},{"hand_raw":"[678s,3]4699m789p123s5m|WW0000","max_fans":[{"count":1,"name":"花龙","points":8}],"record_id":"jTXrCv4d","session_id":"fHmHb7VG","starting_hand_raw":"346689m259p366sF|WW0000","timestamp_ms":1746622269722,"total_fan":11,"win_type":"ron"},{"hand_raw":"[123m,3]34567m44678s5m|NE1000","max_fans":[{"count":1,"name":"一色三连环","points":16}],"record_id":"Bzza2tB8","session_id":"fHmHb7VG","starting_hand_raw":"123457m38p14469sN|NE0000","timestamp_ms":1746622964789,"total_fan":20,"win_type":"tsumo"},{"hand_raw":"[789p,3][456p,3]44m12p789s3p|NN0000","max_fans":[{"count":1,"name":"清龙","points":16}],"record_id":"vstzogdf","session_id":"fHmHb7VG","starting_hand_raw":"4m11278p1789sWFP|NN0000","timestamp_ms":1746623136671,"total_fan":23,"win_type":"ron"}]}