{"current_elo":2056.0,"elo_history":[{"elo":2006.0,"record_id":"9tvutHQ3","session_id":"JMaHwLfd","timestamp_ms":1758112031940},{"elo":2006.0,"record_id":"DtYSmgfu","session_id":"JMaHwLfd","timestamp_ms":1758112149186},{"elo":2006.0,"record_id":"miAHpJEz","session_id":"JMaHwLfd","timestamp_ms":1758112212916},{"elo":2006.0,"record_id":"tb8XfKRM","session_id":"JMaHwLfd","timestamp_ms":1758112336017},{"elo":2006.0,"record_id":"foRJ77uz","session_id":"JMaHwLfd","timestamp_ms":1758112520125},{"elo":2006.0,"record_id":"38BD3oRk","session_id":"JMaHwLfd","timestamp_ms":1758112638649},{"elo":2006.0,"record_id":"K47C7Hgi","session_id":"JMaHwLfd","timestamp_ms":1758112821955},{"elo":2006.0,"record_id":"ECGrM8r1","session_id":"JMaHwLfd","timestamp_ms":1758112924801},{"elo":2006.0,"record_id":"i4XHyRp2","session_id":"JMaHwLfd","timestamp_ms":1758113105300},{"elo":2006.0,"record_id":"hRk6JH7L","session_id":"JMaHwLfd","timestamp_ms":1758113396992},{"elo":2006.0,"record_id":"BrH6cQ7q","session_id":"JMaHwLfd","timestamp_ms":1758113588917},{"elo":2006.0,"record_id":"B0hQu1it","session_id":"JMaHwLfd","timestamp_ms":1758113782131},{"elo":2006.0,"record_id":"oh3cFPY7","session_id":"JMaHwLfd","timestamp_ms":1758113938232},{"elo":2006.0,"record_id":"nciuqB7a","session_id":"JMaHwLfd","timestamp_ms":1758114140436},{"elo":2006.0,"record_id":"Vr6CDCqq","session_id":"JMaHwLfd","timestamp_ms":1758114265970},{"elo":2006.0,"record_id":"ozFu7uzM","session_id":"JMaHwLfd","timestamp_ms":1758114407768},{"elo":2041.0,"record_id":"jAUm5qP5","session_id":"nAmX7i33","timestamp_ms":1758114915663},{"elo":2041.0,"record_id":"VFzf4iYV","session_id":"nAmX7i33","timestamp_ms":1758115094584},{"elo":2041.0,"record_id":"Be4BvhV6","session_id":"nAmX7i33","timestamp_ms":1758115378820},{"elo":2041.0,"record_id":"8YVcf3fn","session_id":"nAmX7i33","timestamp_ms":1758115539404},{"elo":2041.0,"record_id":"sQayqgmk","session_id":"nAmX7i33","timestamp_ms":1758115667673},{"elo":2041.0,"record_id":"Wh5vjAvZ","session_id":"nAmX7i33","timestamp_ms":1758115896146},{"elo":2041.0,"record_id":"CrrYS4x0","session_id":"nAmX7i33","timestamp_ms":1758116046382},{"elo":2041.0,"record_id":"ciyRcqQf","session_id":"nAmX7i33","timestamp_ms":1758116309596},{"elo":2041.0,"record_id":"6GPcokr4","session_id":"nAmX7i33","timestamp_ms":1758116525407},{"elo":2041.0,"record_id":"iKUfRpxo","session_id":"nAmX7i33","timestamp_ms":1758116669858},{"elo":2041.0,"record_id":"cbqWtfgb","session_id":"nAmX7i33","timestamp_ms":1758116786933},{"elo":2041.0,"record_id":"wesDJT5m","session_id":"nAmX7i33","timestamp_ms":1758117015859},{"elo":2041.0,"record_id":"94SYnDBZ","session_id":"nAmX7i33","timestamp_ms":1758117246409},{"elo":2041.0,"record_id":"qjJC6cV9","session_id":"nAmX7i33","timestamp_ms":1758117505920},{"elo":2041.0,"record_id":"8E9si9Qb","session_id":"nAmX7i33","timestamp_ms":1758117684174},{"elo":2041.0,"record_id":"7NM5czxZ","session_id":"nAmX7i33","timestamp_ms":1758117891080},{"elo":2037.0,"record_id":"JZGHcWvA","session_id":"RarhGLxm","timestamp_ms":1758283665506},{"elo":2037.0,"record_id":"vPKk7ir3","session_id":"RarhGLxm","timestamp_ms":1758283777842},{"elo":2037.0,"record_id":"mYaubxFW","session_id":"RarhGLxm","timestamp_ms":1758283972237},{"elo":2037.0,"record_id":"FywyVFVd","session_id":"RarhGLxm","timestamp_ms":1758284210460},{"elo":2037.0,"record_id":"P4xAcA6K","session_id":"RarhGLxm","timestamp_ms":1758284386749},{"elo":2037.0,"record_id":"EUm1XYTi","session_id":"RarhGLxm","timestamp_ms":1758284556463},{"elo":2037.0,"record_id":"sA7Ctviz","session_id":"RarhGLxm","timestamp_ms":1758284710216},{"elo":2037.0,"record_id":"4ojUZ26f","session_id":"RarhGLxm","timestamp_ms":1758284910435},{"elo":2037.0,"record_id":"8pz9zVR1","session_id":"RarhGLxm","timestamp_ms":1758285055902},{"elo":2037.0,"record_id":"PexKTQbv","session_id":"RarhGLxm","timestamp_ms":1758285332467},{"elo":2037.0,"record_id":"21VG5Fs1","session_id":"RarhGLxm","timestamp_ms":1758285659738},{"elo":2037.0,"record_id":"1A5W5r6H","session_id":"RarhGLxm","timestamp_ms":1758285947017},{"elo":2037.0,"record_id":"p2iUBSZt","session_id":"RarhGLxm","timestamp_ms":1758286164390},{"elo":2037.0,"record_id":"GD5eXVEx","session_id":"RarhGLxm","timestamp_ms":1758286360766},{"elo":2037.0,"record_id":"TxVCM5mf","session_id":"RarhGLxm","timestamp_ms":1758286546693},{"elo":2037.0,"record_id":"spJ3VnsW","session_id":"RarhGLxm","timestamp_ms":1758286688222},{"elo":2006.0,"record_id":"EAi2QxNY","session_id":"hLPA55N1","timestamp_ms":1758548708962},{"elo":2006.0,"record_id":"e1hpzTcT","session_id":"hLPA55N1","timestamp_ms":1758548847822},{"elo":2006.0,"record_id":"rs4DnKBn","session_id":"hLPA55N1","timestamp_ms":1758548963280},{"elo":2006.0,"record_id":"2GKj3YdL","session_id":"hLPA55N1","timestamp_ms":1758549077482},{"elo":2006.0,"record_id":"UNJQsAU7","session_id":"hLPA55N1","timestamp_ms":1758549123727},{"elo":2006.0,"record_id":"YbWc1TPA","session_id":"hLPA55N1","timestamp_ms":1758549293003},{"elo":2006.0,"record_id":"8jBidmGc","session_id":"hLPA55N1","timestamp_ms":1758549408131},{"elo":2006.0,"record_id":"7tc1DX17","session_id":"hLPA55N1","timestamp_ms":1758549522306},{"elo":2006.0,"record_id":"J4mnWL2B","session_id":"hLPA55N1","timestamp_ms":1758549696941},{"elo":2006.0,"record_id":"iohSnEWr","session_id":"hLPA55N1","timestamp_ms":1758549788998},{"elo":2006.0,"record_id":"vm7ysiHT","session_id":"hLPA55N1","timestamp_ms":1758549917148},{"elo":2006.0,"record_id":"GL296UVN","session_id":"hLPA55N1","timestamp_ms":1758550053747},{"elo":2006.0,"record_id":"wtWvg1Ts","session_id":"hLPA55N1","timestamp_ms":1758550190622},{"elo":2006.0,"record_id":"w3LFkDHf","session_id":"hLPA55N1","timestamp_ms":1758550311704},{"elo":2006.0,"record_id":"vBwVkoXw","session_id":"hLPA55N1","timestamp_ms":1758550476441},{"elo":2006.0,"record_id":"4ja9MgGq","session_id":"hLPA55N1","timestamp_ms":1758550698199},{"elo":2008.0,"record_id":"4DNuSUsb","session_id":"fnDwd1Vu","timestamp_ms":1758631627872},{"elo":2008.0,"record_id":"KGH133GV","session_id":"fnDwd1Vu","timestamp_ms":1758631759613},{"elo":2008.0,"record_id":"2WAMMtzn","session_id":"fnDwd1Vu","timestamp_ms":1758631974483},{"elo":2008.0,"record_id":"LeL3Gbsh","session_id":"fnDwd1Vu","timestamp_ms":1758632077830},{"elo":2008.0,"record_id":"RHYUx9C9","session_id":"fnDwd1Vu","timestamp_ms":1758632257698},{"elo":2008.0,"record_id":"gLSbYi1L","session_id":"fnDwd1Vu","timestamp_ms":1758632403758},{"elo":2008.0,"record_id":"PZWtHPG8","session_id":"fnDwd1Vu","timestamp_ms":1758632668723},{"elo":2008.0,"record_id":"1w3pvEyG","session_id":"fnDwd1Vu","timestamp_ms":1758632773186},{"elo":2008.0,"record_id":"pognK0Ji","session_id":"fnDwd1Vu","timestamp_ms":1758633021873},{"elo":2008.0,"record_id":"QkN4cMf6","session_id":"fnDwd1Vu","timestamp_ms":1758633157298},{"elo":2008.0,"record_id":"F4SZTxfG","session_id":"fnDwd1Vu","timestamp_ms":1758633297429},{"elo":2008.0,"record_id":"vqyK0DJA","session_id":"fnDwd1Vu","timestamp_ms":1758633614148},{"elo":2008.0,"record_id":"i4UCCUm5","session_id":"fnDwd1Vu","timestamp_ms":1758633761222},{"elo":2008.0,"record_id":"9c4AtPLA","session_id":"fnDwd1Vu","timestamp_ms":1758633916997},{"elo":2008.0,"record_id":"71jqNSdj","session_id":"fnDwd1Vu","timestamp_ms":1758634182623},{"elo":2008.0,"record_id":"J6eXEy6C","session_id":"fnDwd1Vu","timestamp_ms":1758634448374},{"elo":2001.0,"record_id":"bmYkyhQQ","session_id":"XMXxUCca","timestamp_ms":1758715410850},{"elo":2001.0,"record_id":"A8tAovnm","session_id":"XMXxUCca","timestamp_ms":1758715574223},{"elo":2001.0,"record_id":"EpCg18fQ","session_id":"XMXxUCca","timestamp_ms":1758715682696},{"elo":2001.0,"record_id":"ndqX3n7Z","session_id":"XMXxUCca","timestamp_ms":1758715826416},{"elo":2001.0,"record_id":"Q7SazFbh","session_id":"XMXxUCca","timestamp_ms":1758715948296},{"elo":2001.0,"record_id":"GB9iV8nD","session_id":"XMXxUCca","timestamp_ms":1758716251110},{"elo":2001.0,"record_id":"k3QA6SQH","session_id":"XMXxUCca","timestamp_ms":1758716469202},{"elo":2001.0,"record_id":"5RoTPa6V","session_id":"XMXxUCca","timestamp_ms":1758716631705},{"elo":2001.0,"record_id":"e6j3HPL4","session_id":"XMXxUCca","timestamp_ms":1758716766569},{"elo":2001.0,"record_id":"9RR0ypR9","session_id":"XMXxUCca","timestamp_ms":1758716919916},{"elo":2001.0,"record_id":"KcanFd8s","session_id":"XMXxUCca","timestamp_ms":1758717073577},{"elo":2001.0,"record_id":"afav0RTj","session_id":"XMXxUCca","timestamp_ms":1758717223263},{"elo":2001.0,"record_id":"iRu3LR7b","session_id":"XMXxUCca","timestamp_ms":1758717403991},{"elo":2001.0,"record_id":"RfGL2cJQ","session_id":"XMXxUCca","timestamp_ms":1758717678935},{"elo":2001.0,"record_id":"CtnDErSD","session_id":"XMXxUCca","timestamp_ms":1758717794993},{"elo":2001.0,"record_id":"44fVtTEb","session_id":"XMXxUCca","timestamp_ms":1758718000235},{"elo":2006.0,"record_id":"SiXxmxuT","session_id":"Xy2hzmzP","timestamp_ms":1759413069281},{"elo":2006.0,"record_id":"wEgJ7uZk","session_id":"Xy2hzmzP","timestamp_ms":1759413182898},{"elo":2006.0,"record_id":"PR3UTz0x","session_id":"Xy2hzmzP","timestamp_ms":1759413426962},{"elo":2006.0,"record_id":"DiusFx3u","session_id":"Xy2hzmzP","timestamp_ms":1759413606982},{"elo":2006.0,"record_id":"uX9m5q0g","session_id":"Xy2hzmzP","timestamp_ms":1759413843735},{"elo":2006.0,"record_id":"Pv4eEbEi","session_id":"Xy2hzmzP","timestamp_ms":1759414045901},{"elo":2006.0,"record_id":"P4tzJmu5","session_id":"Xy2hzmzP","timestamp_ms":1759414315041},{"elo":2006.0,"record_id":"bFM6X7SF","session_id":"Xy2hzmzP","timestamp_ms":1759414516263},{"elo":2006.0,"record_id":"eLWgNsA3","session_id":"Xy2hzmzP","timestamp_ms":1759414640319},{"elo":2006.0,"record_id":"iLxGrSDV","session_id":"Xy2hzmzP","timestamp_ms":1759414772494},{"elo":2006.0,"record_id":"qS8RPAUd","session_id":"Xy2hzmzP","timestamp_ms":1759414886283},{"elo":2006.0,"record_id":"BvVYxk26","session_id":"Xy2hzmzP","timestamp_ms":1759415133306},{"elo":2006.0,"record_id":"YUWv966w","session_id":"Xy2hzmzP","timestamp_ms":1759415266870},{"elo":2006.0,"record_id":"FhuCY7EU","session_id":"Xy2hzmzP","timestamp_ms":1759415464744},{"elo":2006.0,"record_id":"9xJvVQPB","session_id":"Xy2hzmzP","timestamp_ms":1759415569510},{"elo":2006.0,"record_id":"WkVJVKtZ","session_id":"Xy2hzmzP","timestamp_ms":1759415668119},{"elo":2018.0,"record_id":"iCXiZ4mw","session_id":"kvGf40MH","timestamp_ms":1760615443167},{"elo":2018.0,"record_id":"2Sj19ZrJ","session_id":"kvGf40MH","timestamp_ms":1760615561504},{"elo":2018.0,"record_id":"qJ7ttPQV","session_id":"kvGf40MH","timestamp_ms":1760615696570},{"elo":2018.0,"record_id":"dMpSiHwk","session_id":"kvGf40MH","timestamp_ms":1760615837798},{"elo":2018.0,"record_id":"KjUxmhoH","session_id":"kvGf40MH","timestamp_ms":1760615998384},{"elo":2018.0,"record_id":"cWQgitB1","session_id":"kvGf40MH","timestamp_ms":1760616090824},{"elo":2018.0,"record_id":"xQr985eG","session_id":"kvGf40MH","timestamp_ms":1760616234173},{"elo":2018.0,"record_id":"2xsFraG0","session_id":"kvGf40MH","timestamp_ms":1760616364806},{"elo":2018.0,"record_id":"1tRYH6AM","session_id":"kvGf40MH","timestamp_ms":1760616502410},{"elo":2018.0,"record_id":"EinwP7ox","session_id":"kvGf40MH","timestamp_ms":1760616714316},{"elo":2018.0,"record_id":"otqgp6EJ","session_id":"kvGf40MH","timestamp_ms":1760616856107},{"elo":2018.0,"record_id":"Q21rMDR8","session_id":"kvGf40MH","timestamp_ms":1760617025768},{"elo":2018.0,"record_id":"UvPJqLuX","session_id":"kvGf40MH","timestamp_ms":1760617145654},{"elo":2018.0,"record_id":"5Jrc3b7i","session_id":"kvGf40MH","timestamp_ms":1760617300775},{"elo":2018.0,"record_id":"S7203XMU","session_id":"kvGf40MH","timestamp_ms":1760617448864},{"elo":2018.0,"record_id":"REvCK0QE","session_id":"kvGf40MH","timestamp_ms":1760617609824},{"elo":2052.0,"record_id":"BLxzezm4","session_id":"UET06p4U","timestamp_ms":1760793823159},{"elo":2052.0,"record_id":"bCfpfSsc","session_id":"UET06p4U","timestamp_ms":1760793993368},{"elo":2052.0,"record_id":"AUkAnE6t","session_id":"UET06p4U","timestamp_ms":1760794073770},{"elo":2052.0,"record_id":"LSsy6JRo","session_id":"UET06p4U","timestamp_ms":1760794224515},{"elo":2052.0,"record_id":"8YVfRkjQ","session_id":"UET06p4U","timestamp_ms":1760794417121},{"elo":2052.0,"record_id":"gPEa14An","session_id":"UET06p4U","timestamp_ms":1760794668630},{"elo":2052.0,"record_id":"bXQDEvBQ","session_id":"UET06p4U","timestamp_ms":1760794782996},{"elo":2052.0,"record_id":"oUqkLP6h","session_id":"UET06p4U","timestamp_ms":1760794878760},{"elo":2052.0,"record_id":"nQW2vAqq","session_id":"UET06p4U","timestamp_ms":1760795073347},{"elo":2052.0,"record_id":"NYB9XUjG","session_id":"UET06p4U","timestamp_ms":1760795226674},{"elo":2052.0,"record_id":"QmXvvNG6","session_id":"UET06p4U","timestamp_ms":1760795371252},{"elo":2052.0,"record_id":"VdnKrofB","session_id":"UET06p4U","timestamp_ms":1760795484403},{"elo":2052.0,"record_id":"F61SZXcx","session_id":"UET06p4U","timestamp_ms":1760795645172},{"elo":2052.0,"record_id":"B8k4yH7L","session_id":"UET06p4U","timestamp_ms":1760795877326},{"elo":2052.0,"record_id":"jpZeirQC","session_id":"UET06p4U","timestamp_ms":1760796002369},{"elo":2052.0,"record_id":"iKUiCXA6","session_id":"UET06p4U","timestamp_ms":1760796173367},{"elo":2066.0,"record_id":"F782QRkK","session_id":"KLEWXenb","timestamp_ms":1760968126731},{"elo":2066.0,"record_id":"THb9cn08","session_id":"KLEWXenb","timestamp_ms":1760968211549},{"elo":2066.0,"record_id":"eLZjNSLr","session_id":"KLEWXenb","timestamp_ms":1760968288970},{"elo":2066.0,"record_id":"EVsy95iP","session_id":"KLEWXenb","timestamp_ms":1760968388967},{"elo":2066.0,"record_id":"LiYFn1zG","session_id":"KLEWXenb","timestamp_ms":1760968492376},{"elo":2066.0,"record_id":"1jNrMM1d","session_id":"KLEWXenb","timestamp_ms":1760968610621},{"elo":2066.0,"record_id":"TojQJmEQ","session_id":"KLEWXenb","timestamp_ms":1760968688157},{"elo":2066.0,"record_id":"SjHgkHjU","session_id":"KLEWXenb","timestamp_ms":1760968786910},{"elo":2066.0,"record_id":"Xb83u8k8","session_id":"KLEWXenb","timestamp_ms":1760968937245},{"elo":2066.0,"record_id":"ifDhBV9Q","session_id":"KLEWXenb","timestamp_ms":1760969033015},{"elo":2066.0,"record_id":"Mwje50BH","session_id":"KLEWXenb","timestamp_ms":1760969135685},{"elo":2066.0,"record_id":"wziFWWyF","session_id":"KLEWXenb","timestamp_ms":1760969266450},{"elo":2066.0,"record_id":"nxTY37z5","session_id":"KLEWXenb","timestamp_ms":1760969454203},{"elo":2066.0,"record_id":"jsHza4zD","session_id":"KLEWXenb","timestamp_ms":1760969590174},{"elo":2066.0,"record_id":"5SvBYwCD","session_id":"KLEWXenb","timestamp_ms":1760969641345},{"elo":2066.0,"record_id":"bw16P7Ud","session_id":"KLEWXenb","timestamp_ms":1760969776556},{"elo":1969.0,"record_id":"DiuteccQ","session_id":"Q09dAxYF","timestamp_ms":1761051572952},{"elo":1969.0,"record_id":"ghpSTnD5","session_id":"Q09dAxYF","timestamp_ms":1761051710108},{"elo":1969.0,"record_id":"fr0egmwF","session_id":"Q09dAxYF","timestamp_ms":1761051899765},{"elo":1969.0,"record_id":"c8GzvLrk","session_id":"Q09dAxYF","timestamp_ms":1761052090783},{"elo":1969.0,"record_id":"SS8NiJcL","session_id":"Q09dAxYF","timestamp_ms":1761052350241},{"elo":1969.0,"record_id":"2ZWUgGB0","session_id":"Q09dAxYF","timestamp_ms":1761052474115},{"elo":1969.0,"record_id":"CkgEy53P","session_id":"Q09dAxYF","timestamp_ms":1761052586901},{"elo":1969.0,"record_id":"RbxjULkZ","session_id":"Q09dAxYF","timestamp_ms":1761052741667},{"elo":1969.0,"record_id":"0sw3m3F4","session_id":"Q09dAxYF","timestamp_ms":1761052881053},{"elo":1969.0,"record_id":"SjEf8QsK","session_id":"Q09dAxYF","timestamp_ms":1761053047224},{"elo":1969.0,"record_id":"jWzSfmty","session_id":"Q09dAxYF","timestamp_ms":1761053173840},{"elo":1969.0,"record_id":"wUQymExw","session_id":"Q09dAxYF","timestamp_ms":1761053262908},{"elo":1969.0,"record_id":"nfJFPq8r","session_id":"Q09dAxYF","timestamp_ms":1761053385799},{"elo":1969.0,"record_id":"moVUJfK7","session_id":"Q09dAxYF","timestamp_ms":1761053568160},{"elo":1969.0,"record_id":"D7TsGd7z","session_id":"Q09dAxYF","timestamp_ms":1761053725633},{"elo":1969.0,"record_id":"nxQWSFFc","session_id":"Q09dAxYF","timestamp_ms":1761053835863},{"elo":2038.0,"record_id":"FjWyw8iQ","session_id":"F6pB1UgG","timestamp_ms":1761139493159},{"elo":2038.0,"record_id":"recPo0xJ","session_id":"F6pB1UgG","timestamp_ms":1761139559106},{"elo":2038.0,"record_id":"qnochquZ","session_id":"F6pB1UgG","timestamp_ms":1761139755382},{"elo":2038.0,"record_id":"orF51ApY","session_id":"F6pB1UgG","timestamp_ms":1761139893095},{"elo":2038.0,"record_id":"L1EnYp09","session_id":"F6pB1UgG","timestamp_ms":1761140027231},{"elo":2038.0,"record_id":"sqsdbR8C","session_id":"F6pB1UgG","timestamp_ms":1761140189131},{"elo":2038.0,"record_id":"b4EvzTHV","session_id":"F6pB1UgG","timestamp_ms":1761140282631},{"elo":2038.0,"record_id":"2PKLnUpN","session_id":"F6pB1UgG","timestamp_ms":1761140374505},{"elo":2038.0,"record_id":"j3b1uUyA","session_id":"F6pB1UgG","timestamp_ms":1761140457229},{"elo":2038.0,"record_id":"mFQhy6cz","session_id":"F6pB1UgG","timestamp_ms":1761140582993},{"elo":2038.0,"record_id":"9H0dmHvB","session_id":"F6pB1UgG","timestamp_ms":1761140698660},{"elo":2038.0,"record_id":"AexercNQ","session_id":"F6pB1UgG","timestamp_ms":1761140865829},{"elo":2038.0,"record_id":"7Zo5ghX0","session_id":"F6pB1UgG","timestamp_ms":1761141113831},{"elo":2038.0,"record_id":"RhxnbQzd","session_id":"F6pB1UgG","timestamp_ms":1761141254572},{"elo":2038.0,"record_id":"8wr8c6EM","session_id":"F6pB1UgG","timestamp_ms":1761141407802},{"elo":2038.0,"record_id":"gzPYwVpV","session_id":"F6pB1UgG","timestamp_ms":1761141563247},{"elo":2001.0,"record_id":"FVaNwmTu","session_id":"1tY4ziSt","timestamp_ms":1761220716679},{"elo":2001.0,"record_id":"Gr0J0xUv","session_id":"1tY4ziSt","timestamp_ms":1761221011391},{"elo":2001.0,"record_id":"gjkGyNMo","session_id":"1tY4ziSt","timestamp_ms":1761221237161},{"elo":2001.0,"record_id":"FMgQrcNp","session_id":"1tY4ziSt","timestamp_ms":1761221380379},{"elo":2001.0,"record_id":"k62gb76L","session_id":"1tY4ziSt","timestamp_ms":1761221640754},{"elo":2001.0,"record_id":"dWGjcakk","session_id":"1tY4ziSt","timestamp_ms":1761221832962},{"elo":2001.0,"record_id":"Ljf1JmLr","session_id":"1tY4ziSt","timestamp_ms":1761222121098},{"elo":2001.0,"record_id":"3n2VNqwL","session_id":"1tY4ziSt","timestamp_ms":1761222260266},{"elo":2001.0,"record_id":"QX3fu9Hc","session_id":"1tY4ziSt","timestamp_ms":1761222430249},{"elo":2001.0,"record_id":"fbGu0iQo","session_id":"1tY4ziSt","timestamp_ms":1761222610320},{"elo":2001.0,"record_id":"H4txwCBH","session_id":"1tY4ziSt","timestamp_ms":1761222897190},{"elo":2001.0,"record_id":"qnkgdioT","session_id":"1tY4ziSt","timestamp_ms":1761223114913},{"elo":2001.0,"record_id":"ftP938XZ","session_id":"1tY4ziSt","timestamp_ms":1761223262354},{"elo":2001.0,"record_id":"UrwiP8An","session_id":"1tY4ziSt","timestamp_ms":1761223438517},{"elo":2001.0,"record_id":"5URytFPF","session_id":"1tY4ziSt","timestamp_ms":1761223738858},{"elo":2001.0,"record_id":"aCoDvtpC","session_id":"1tY4ziSt","timestamp_ms":1761223971026},{"elo":2012.0,"record_id":"fGzugnJJ","session_id":"q6jxB6Up","timestamp_ms":1762260314604},{"elo":2012.0,"record_id":"k8qGqd1c","session_id":"q6jxB6Up","timestamp_ms":1762260579310},{"elo":2012.0,"record_id":"KQoc7Huf","session_id":"q6jxB6Up","timestamp_ms":1762260783659},{"elo":2012.0,"record_id":"sERT9wxX","session_id":"q6jxB6Up","timestamp_ms":1762260959231},{"elo":2012.0,"record_id":"qGeq6WFT","session_id":"q6jxB6Up","timestamp_ms":1762261107080},{"elo":2012.0,"record_id":"8fSNQRqw","session_id":"q6jxB6Up","timestamp_ms":1762261381733},{"elo":2012.0,"record_id":"hrcC3wT0","session_id":"q6jxB6Up","timestamp_ms":1762261581315},{"elo":2012.0,"record_id":"gnAUVTx4","session_id":"q6jxB6Up","timestamp_ms":1762261895153},{"elo":2012.0,"record_id":"wqAcEGFw","session_id":"q6jxB6Up","timestamp_ms":1762262039108},{"elo":2012.0,"record_id":"cqvBNC06","session_id":"q6jxB6Up","timestamp_ms":1762262225551},{"elo":2012.0,"record_id":"eBL6SP9o","session_id":"q6jxB6Up","timestamp_ms":1762262380212},{"elo":2012.0,"record_id":"t9uWcjZS","session_id":"q6jxB6Up","timestamp_ms":1762262567373},{"elo":2012.0,"record_id":"bQVuNWnf","session_id":"q6jxB6Up","timestamp_ms":1762262872669},{"elo":2012.0,"record_id":"Z3W9dn4U","session_id":"q6jxB6Up","timestamp_ms":1762262983880},{"elo":2012.0,"record_id":"PNAdPdX1","session_id":"q6jxB6Up","timestamp_ms":1762263359091},{"elo":2012.0,"record_id":"v8UoidUz","session_id":"q6jxB6Up","timestamp_ms":1762263618385},{"elo":1959.0,"record_id":"R4XaMwCE","session_id":"LzE7tcLJ","timestamp_ms":1764502839588},{"elo":1959.0,"record_id":"dtMt8fdi","session_id":"LzE7tcLJ","timestamp_ms":1764502920607},{"elo":1959.0,"record_id":"p4XeRUW6","session_id":"LzE7tcLJ","timestamp_ms":1764503063266},{"elo":1959.0,"record_id":"4MrcDJ9w","session_id":"LzE7tcLJ","timestamp_ms":1764503199821},{"elo":1959.0,"record_id":"t4yFauK0","session_id":"LzE7tcLJ","timestamp_ms":1764503384626},{"elo":1959.0,"record_id":"DfaTZkEe","session_id":"LzE7tcLJ","timestamp_ms":1764503524768},{"elo":1959.0,"record_id":"4exsFigz","session_id":"LzE7tcLJ","timestamp_ms":1764503715344},{"elo":1959.0,"record_id":"9WoEQZYy","session_id":"LzE7tcLJ","timestamp_ms":1764503888963},{"elo":1959.0,"record_id":"0haVD4aq","session_id":"LzE7tcLJ","timestamp_ms":1764504048174},{"elo":1959.0,"record_id":"cUtjeYp5","session_id":"LzE7tcLJ","timestamp_ms":1764504232093},{"elo":1959.0,"record_id":"gUWGXxDc","session_id":"LzE7tcLJ","timestamp_ms":1764504289310},{"elo":1959.0,"record_id":"PiPcroEF","session_id":"LzE7tcLJ","timestamp_ms":1764504354864},{"elo":1959.0,"record_id":"pj7WpwKQ","session_id":"LzE7tcLJ","timestamp_ms":1764504537203},{"elo":1959.0,"record_id":"mdxyLtAs","session_id":"LzE7tcLJ","timestamp_ms":1764504806489},{"elo":1959.0,"record_id":"kmk8nGvu","session_id":"LzE7tcLJ","timestamp_ms":1764504934633},{"elo":1959.0,"record_id":"P8H5Q8UM","session_id":"LzE7tcLJ","timestamp_ms":1764505071019},{"elo":2026.0,"record_id":"8kiJqgz9","session_id":"F5KimPM3","timestamp_ms":1764936052398},{"elo":2026.0,"record_id":"rmVvUHda","session_id":"F5KimPM3","timestamp_ms":1764936329678},{"elo":2026.0,"record_id":"F17pYMci","session_id":"F5KimPM3","timestamp_ms":1764936600835},{"elo":2026.0,"record_id":"ncihK6oD","session_id":"F5KimPM3","timestamp_ms":1764936763014},{"elo":2026.0,"record_id":"ozFgcqf0","session_id":"F5KimPM3","timestamp_ms":1764936873432},{"elo":2026.0,"record_id":"fA2wRLEq","session_id":"F5KimPM3","timestamp_ms":1764937187304},{"elo":2026.0,"record_id":"szhHnFTu","session_id":"F5KimPM3","timestamp_ms":1764937356886},{"elo":2026.0,"record_id":"vD34A8s3","session_id":"F5KimPM3","timestamp_ms":1764937497148},{"elo":2026.0,"record_id":"u8cLbgM7","session_id":"F5KimPM3","timestamp_ms":1764937583802},{"elo":2026.0,"record_id":"ZGR32DRF","session_id":"F5KimPM3","timestamp_ms":1764937724241},{"elo":2026.0,"record_id":"pKRAn1bS","session_id":"F5KimPM3","timestamp_ms":1764938011945},{"elo":2026.0,"record_id":"sQamKcSP","session_id":"F5KimPM3","timestamp_ms":1764938275483},{"elo":2026.0,"record_id":"hjfDoVPX","session_id":"F5KimPM3","timestamp_ms":1764938383363},{"elo":2026.0,"record_id":"qVyN8VLk","session_id":"F5KimPM3","timestamp_ms":1764938530430},{"elo":2026.0,"record_id":"Mfy4g6CF","session_id":"F5KimPM3","timestamp_ms":1764938783841},{"elo":2026.0,"record_id":"UmyGo16J","session_id":"F5KimPM3","timestamp_ms":1764939034935},{"elo":2069.0,"record_id":"6Pzo4To4","session_id":"FvaMNV2z","timestamp_ms":1766752938708},{"elo":2069.0,"record_id":"5Zp88eSS","session_id":"FvaMNV2z","timestamp_ms":1766753033085},{"elo":2069.0,"record_id":"SLMPzDqQ","session_id":"FvaMNV2z","timestamp_ms":1766753244836},{"elo":2069.0,"record_id":"9aEkJ4Yh","session_id":"FvaMNV2z","timestamp_ms":1766753422413},{"elo":2069.0,"record_id":"BobWgxwr","session_id":"FvaMNV2z","timestamp_ms":1766753628115},{"elo":2069.0,"record_id":"UaXFKzJ3","session_id":"FvaMNV2z","timestamp_ms":1766753745557},{"elo":2069.0,"record_id":"Aj9o7W1d","session_id":"FvaMNV2z","timestamp_ms":1766753837742},{"elo":2069.0,"record_id":"aayeGCwC","session_id":"FvaMNV2z","timestamp_ms":1766753992587},{"elo":2069.0,"record_id":"jQ5P1JDT","session_id":"FvaMNV2z","timestamp_ms":1766754069097},{"elo":2069.0,"record_id":"Zj9sB3UA","session_id":"FvaMNV2z","timestamp_ms":1766754164626},{"elo":2069.0,"record_id":"7eiH5PEL","session_id":"FvaMNV2z","timestamp_ms":1766754254534},{"elo":2069.0,"record_id":"1uY2X69E","session_id":"FvaMNV2z","timestamp_ms":1766754347356},{"elo":2069.0,"record_id":"qfVuQq7r","session_id":"FvaMNV2z","timestamp_ms":1766754418683},{"elo":2069.0,"record_id":"ug2X1eEw","session_id":"FvaMNV2z","timestamp_ms":1766754586728},{"elo":2069.0,"record_id":"403E9DXe","session_id":"FvaMNV2z","timestamp_ms":1766754679727},{"elo":2069.0,"record_id":"Nyhd1mdU","session_id":"FvaMNV2z","timestamp_ms":1766754887477},{"elo":2080.0,"record_id":"1Q6qxuEh","session_id":"Gzc3rC7D","timestamp_ms":1766755483083},{"elo":2080.0,"record_id":"gYpU4p3M","session_id":"Gzc3rC7D","timestamp_ms":1766755623327},{"elo":2080.0,"record_id":"Qe0ZwgDB","session_id":"Gzc3rC7D","timestamp_ms":1766755737951},{"elo":2080.0,"record_id":"J4miHS4i","session_id":"Gzc3rC7D","timestamp_ms":1766755910789},{"elo":2080.0,"record_id":"HBqrykHH","session_id":"Gzc3rC7D","timestamp_ms":1766756170266},{"elo":2080.0,"record_id":"mvP482u7","session_id":"Gzc3rC7D","timestamp_ms":1766756356788},{"elo":2080.0,"record_id":"U4RdiAAY","session_id":"Gzc3rC7D","timestamp_ms":1766756563629},{"elo":2080.0,"record_id":"L88kXBwZ","session_id":"Gzc3rC7D","timestamp_ms":1766756661631},{"elo":2080.0,"record_id":"3LPzNXnX","session_id":"Gzc3rC7D","timestamp_ms":1766756845314},{"elo":2080.0,"record_id":"EQVcftBo","session_id":"Gzc3rC7D","timestamp_ms":1766757004845},{"elo":2080.0,"record_id":"ATDF4e3t","session_id":"Gzc3rC7D","timestamp_ms":1766757156728},{"elo":2080.0,"record_id":"iGk4HA9p","session_id":"Gzc3rC7D","timestamp_ms":1766757231955},{"elo":2080.0,"record_id":"dRJkJbrD","session_id":"Gzc3rC7D","timestamp_ms":1766757392821},{"elo":2080.0,"record_id":"KZxH67iU","session_id":"Gzc3rC7D","timestamp_ms":1766757485809},{"elo":2080.0,"record_id":"Sf8Rds7H","session_id":"Gzc3rC7D","timestamp_ms":1766757585434},{"elo":2080.0,"record_id":"RojfeSMZ","session_id":"Gzc3rC7D","timestamp_ms":1766757765559},{"elo":2000.0,"record_id":"BxQ2LXWe","session_id":"9i3Jrmkn","timestamp_ms":1767096188330},{"elo":2000.0,"record_id":"kdKdELkD","session_id":"9i3Jrmkn","timestamp_ms":1767096422208},{"elo":2000.0,"record_id":"sivoZfXT","session_id":"9i3Jrmkn","timestamp_ms":1767096549194},{"elo":2000.0,"record_id":"a60LQf3n","session_id":"9i3Jrmkn","timestamp_ms":1767096849426},{"elo":2000.0,"record_id":"u6GrSZxp","session_id":"9i3Jrmkn","timestamp_ms":1767097010366},{"elo":2000.0,"record_id":"LQYCfRM9","session_id":"9i3Jrmkn","timestamp_ms":1767097144733},{"elo":2000.0,"record_id":"pVmKKRZS","session_id":"9i3Jrmkn","timestamp_ms":1767097250661},{"elo":2000.0,"record_id":"YcaYLfpq","session_id":"9i3Jrmkn","timestamp_ms":1767097427137},{"elo":2000.0,"record_id":"bi37rmJS","session_id":"9i3Jrmkn","timestamp_ms":1767097575834},{"elo":2000.0,"record_id":"NwZ140tH","session_id":"9i3Jrmkn","timestamp_ms":1767097719687},{"elo":2000.0,"record_id":"vm4qGZ9e","session_id":"9i3Jrmkn","timestamp_ms":1767097937708},{"elo":2000.0,"record_id":"Y3H35WQx","session_id":"9i3Jrmkn","timestamp_ms":1767098028917},{"elo":2000.0,"record_id":"ks7LsEZ4","session_id":"9i3Jrmkn","timestamp_ms":1767098185967},{"elo":2000.0,"record_id":"6RvVFw1D","session_id":"9i3Jrmkn","timestamp_ms":1767098349331},{"elo":2000.0,"record_id":"nE4MxYsc","session_id":"9i3Jrmkn","timestamp_ms":1767098450052},{"elo":2000.0,"record_id":"9bmQhx64","session_id":"9i3Jrmkn","timestamp_ms":1767098567551},{"elo":2056.0,"record_id":"xFFQ5EoQ","session_id":"XL6M8A3z","timestamp_ms":1767098891206},{"elo":2056.0,"record_id":"RogbGB2Y","session_id":"XL6M8A3z","timestamp_ms":1767099122149},{"elo":2056.0,"record_id":"ecWujmSV","session_id":"XL6M8A3z","timestamp_ms":1767099279309},{"elo":2056.0,"record_id":"EnE9cAPQ","session_id":"XL6M8A3z","timestamp_ms":1767099414788},{"elo":2056.0,"record_id":"4tGfW1d5","session_id":"XL6M8A3z","timestamp_ms":1767099579397},{"elo":2056.0,"record_id":"01SJjsdi","session_id":"XL6M8A3z","timestamp_ms":1767099758657},{"elo":2056.0,"record_id":"foN5Mu0f","session_id":"XL6M8A3z","timestamp_ms":1767099850649},{"elo":2056.0,"record_id":"B6m35pbm","session_id":"XL6M8A3z","timestamp_ms":1767099995599},{"elo":2056.0,"record_id":"aysuttrs","session_id":"XL6M8A3z","timestamp_ms":1767100103238},{"elo":2056.0,"record_id":"39F5DwXw","session_id":"XL6M8A3z","timestamp_ms":1767100187169},{"elo":2056.0,"record_id":"i4U5DCe6","session_id":"XL6M8A3z","timestamp_ms":1767100253268},{"elo":2056.0,"record_id":"uLnF3E9G","session_id":"XL6M8A3z","timestamp_ms":1767100364766},{"elo":2056.0,"record_id":"BrDtsBFF","session_id":"XL6M8A3z","timestamp_ms":1767100496183},{"elo":2056.0,"record_id":"QfUE7Mn1","session_id":"XL6M8A3z","timestamp_ms":1767100695342},{"elo":2056.0,"record_id":"rmSvE7uw","session_id":"XL6M8A3z","timestamp_ms":1767100827736},{"elo":2056.0,"record_id":"hwq8F3V2","session_id":"XL6M8A3z","timestamp_ms":1767100958007}],"name":"Jencese2号","player_id":"s2Rm14bR","processed_records":["9tvutHQ3","DtYSmgfu","miAHpJEz","tb8XfKRM","foRJ77uz","38BD3oRk","K47C7Hgi","ECGrM8r1","i4XHyRp2","hRk6JH7L","BrH6cQ7q","B0hQu1it","oh3cFPY7","nciuqB7a","Vr6CDCqq","ozFu7uzM","jAUm5qP5","VFzf4iYV","Be4BvhV6","8YVcf3fn","sQayqgmk","Wh5vjAvZ","CrrYS4x0","ciyRcqQf","6GPcokr4","iKUfRpxo","cbqWtfgb","wesDJT5m","94SYnDBZ","qjJC6cV9","8E9si9Qb","7NM5czxZ","JZGHcWvA","vPKk7ir3","mYaubxFW","FywyVFVd","P4xAcA6K","EUm1XYTi","sA7Ctviz","4ojUZ26f","8pz9zVR1","PexKTQbv","21VG5Fs1","1A5W5r6H","p2iUBSZt","GD5eXVEx","TxVCM5mf","spJ3VnsW","EAi2QxNY","e1hpzTcT","rs4DnKBn","2GKj3YdL","UNJQsAU7","YbWc1TPA","8jBidmGc","7tc1DX17","J4mnWL2B","iohSnEWr","vm7ysiHT","GL296UVN","wtWvg1Ts","w3LFkDHf","vBwVkoXw","4ja9MgGq","4DNuSUsb","KGH133GV","2WAMMtzn","LeL3Gbsh","RHYUx9C9","gLSbYi1L","PZWtHPG8","1w3pvEyG","pognK0Ji","QkN4cMf6","F4SZTxfG","vqyK0DJA","i4UCCUm5","9c4AtPLA","71jqNSdj","J6eXEy6C","bmYkyhQQ","A8tAovnm","EpCg18fQ","ndqX3n7Z","Q7SazFbh","GB9iV8nD","k3QA6SQH","5RoTPa6V","e6j3HPL4","9RR0ypR9","KcanFd8s","afav0RTj","iRu3LR7b","RfGL2cJQ","CtnDErSD","44fVtTEb","SiXxmxuT","wEgJ7uZk","PR3UTz0x","DiusFx3u","uX9m5q0g","Pv4eEbEi","P4tzJmu5","bFM6X7SF","eLWgNsA3","iLxGrSDV","qS8RPAUd","BvVYxk26","YUWv966w","FhuCY7EU","9xJvVQPB","WkVJVKtZ","iCXiZ4mw","2Sj19ZrJ","qJ7ttPQV","dMpSiHwk","KjUxmhoH","cWQgitB1","xQr985eG","2xsFraG0","1tRYH6AM","EinwP7ox","otqgp6EJ","Q21rMDR8","UvPJqLuX","5Jrc3b7i","S7203XMU","REvCK0QE","BLxzezm4","bCfpfSsc","AUkAnE6t","LSsy6JRo","8YVfRkjQ","gPEa14An","bXQDEvBQ","oUqkLP6h","nQW2vAqq","NYB9XUjG","QmXvvNG6","VdnKrofB","F61SZXcx","B8k4yH7L","jpZeirQC","iKUiCXA6","F782QRkK","THb9cn08","eLZjNSLr","EVsy95iP","LiYFn1zG","1jNrMM1d","TojQJmEQ","SjHgkHjU","Xb83u8k8","ifDhBV9Q","Mwje50BH","wziFWWyF","nxTY37z5","jsHza4zD","5SvBYwCD","bw16P7Ud","DiuteccQ","ghpSTnD5","fr0egmwF","c8GzvLrk","SS8NiJcL","2ZWUgGB0","CkgEy53P","RbxjULkZ","0sw3m3F4","SjEf8QsK","jWzSfmty","wUQymExw","nfJFPq8r","moVUJfK7","D7TsGd7z","nxQWSFFc","FjWyw8iQ","recPo0xJ","qnochquZ","orF51ApY","L1EnYp09","sqsdbR8C","b4EvzTHV","2PKLnUpN","j3b1uUyA","mFQhy6cz","9H0dmHvB","AexercNQ","7Zo5ghX0","RhxnbQzd","8wr8c6EM","gzPYwVpV","FVaNwmTu","Gr0J0xUv","gjkGyNMo","FMgQrcNp","k62gb76L","dWGjcakk","Ljf1JmLr","3n2VNqwL","QX3fu9Hc","fbGu0iQo","H4txwCBH","qnkgdioT","ftP938XZ","UrwiP8An","5URytFPF","aCoDvtpC","fGzugnJJ","k8qGqd1c","KQoc7Huf","sERT9wxX","qGeq6WFT","8fSNQRqw","hrcC3wT0","gnAUVTx4","wqAcEGFw","cqvBNC06","eBL6SP9o","t9uWcjZS","bQVuNWnf","Z3W9dn4U","PNAdPdX1","v8UoidUz","R4XaMwCE","dtMt8fdi","p4XeRUW6","4MrcDJ9w","t4yFauK0","DfaTZkEe","4exsFigz","9WoEQZYy","0haVD4aq","cUtjeYp5","gUWGXxDc","PiPcroEF","pj7WpwKQ","mdxyLtAs","kmk8nGvu","P8H5Q8UM","8kiJqgz9","rmVvUHda","F17pYMci","ncihK6oD","ozFgcqf0","fA2wRLEq","szhHnFTu","vD34A8s3","u8cLbgM7","ZGR32DRF","pKRAn1bS","sQamKcSP","hjfDoVPX","qVyN8VLk","Mfy4g6CF","UmyGo16J","6Pzo4To4","5Zp88eSS","SLMPzDqQ","9aEkJ4Yh","BobWgxwr","UaXFKzJ3","Aj9o7W1d","aayeGCwC","jQ5P1JDT","Zj9sB3UA","7eiH5PEL","1uY2X69E","qfVuQq7r","ug2X1eEw","403E9DXe","Nyhd1mdU","1Q6qxuEh","gYpU4p3M","Qe0ZwgDB","J4miHS4i","HBqrykHH","mvP482u7","U4RdiAAY","L88kXBwZ","3LPzNXnX","EQVcftBo","ATDF4e3t","iGk4HA9p","dRJkJbrD","KZxH67iU","Sf8Rds7H","RojfeSMZ","BxQ2LXWe","kdKdELkD","sivoZfXT","a60LQf3n","u6GrSZxp","LQYCfRM9","pVmKKRZS","YcaYLfpq","bi37rmJS","NwZ140tH","vm4qGZ9e","Y3H35WQx","ks7LsEZ4","6RvVFw1D","nE4MxYsc","9bmQhx64","xFFQ5EoQ","RogbGB2Y","ecWujmSV","EnE9cAPQ","4tGfW1d5","01SJjsdi","foN5Mu0f","B6m35pbm","aysuttrs","39F5DwXw","i4U5DCe6","uLnF3E9G","BrDtsBFF","QfUE7Mn1","rmSvE7uw","hwq8F3V2"],"processed_sessions":["XL6M8A3z","9i3Jrmkn","Xy2hzmzP","XMXxUCca","Gzc3rC7D","nAmX7i33","F6pB1UgG","Q09dAxYF","fnDwd1Vu","1tY4ziSt","kvGf40MH","LzE7tcLJ","hLPA55N1","UET06p4U","KLEWXenb","q6jxB6Up","RarhGLxm","FvaMNV2z","F5KimPM3","JMaHwLfd"],"stats":{"average_step_seconds":1.152111627426684,"deal_in_count":56,"draw_count":5,"ron_win_count":59,"sessions_recorded":20,"total_rounds":320,"total_session_seconds":11157.049000000008,"total_steps":9684,"tsumo_against_count":66,"tsumo_win_count":14,"win_count":73},"wins":[{"hand_raw":"[PPP,3][678p,2]456m444sEE|SW0000","max_fans":[{"count":1,"name":"五门齐","points":6}],"record_id":"foRJ77uz","session_id":"JMaHwLfd","timestamp_ms":1758112520125,"total_fan":9,"win_type":"ron"},{"hand_raw":"667788m111p5588s1p|SS0000","max_fans":[{"count":1,"name":"七对","points":24}],"record_id":"38BD3oRk","session_id":"JMaHwLfd","timestamp_ms":1758112638649,"total_fan":28,"win_type":"ron"},{"hand_raw":"456m45555667p34s5s|WE1000","max_fans":[{"count":1,"name":"全带五","points":16}],"record_id":"hRk6JH7L","session_id":"JMaHwLfd","timestamp_ms":1758113396992,"total_fan":32,"win_type":"tsumo"},{"hand_raw":"[345p,2]234m56779pNN8p|NS0000","max_fans":[{"count":1,"name":"一色三连环","points":16}],"record_id":"ozFu7uzM","session_id":"JMaHwLfd","timestamp_ms":1758114407768,"total_fan":21,"win_type":"ron"},{"hand_raw":"[789s,1][123m,1]55m34p234s5p|SN0000","max_fans":[{"count":1,"name":"三色三步高","points":6}],"record_id":"sQayqgmk","session_id":"nAmX7i33","timestamp_ms":1758115667673,"total_fan":9,"win_type":"ron"},{"hand_raw":"[7777m]2m666p334455s2m|WW0000","max_fans":[{"count":1,"name":"门前清","points":2},{"count":1,"name":"双暗刻","points":2},{"count":1,"name":"暗杠","points":2},{"count":1,"name":"断幺","points":2}],"record_id":"cbqWtfgb","session_id":"nAmX7i33","timestamp_ms":1758116786933,"total_fan":12,"win_type":"ron"},{"hand_raw":"56788m234p23456s7s|WS0000","max_fans":[{"count":1,"name":"门前清","points":2},{"count":1,"name":"平和","points":2},{"count":1,"name":"断幺","points":2}],"record_id":"wesDJT5m","session_id":"nAmX7i33","timestamp_ms":1758117015859,"total_fan":11,"win_type":"ron"},{"hand_raw":"[678p,3]123567m34sNN2s|NS0000","max_fans":[{"count":1,"name":"无番和","points":8}],"record_id":"94SYnDBZ","session_id":"nAmX7i33","timestamp_ms":1758117246409,"total_fan":9,"win_type":"ron"},{"hand_raw":"[8888m]5678p234678s5p|NE1000","max_fans":[{"count":1,"name":"不求人","points":4}],"record_id":"qjJC6cV9","session_id":"nAmX7i33","timestamp_ms":1758117505920,"total_fan":10,"win_type":"tsumo"},{"hand_raw":"44m2244p2246677s4s|EN0000","max_fans":[{"count":1,"name":"七对","points":24}],"record_id":"mYaubxFW","session_id":"RarhGLxm","timestamp_ms":1758283972237,"total_fan":26,"win_type":"ron"},{"hand_raw":"3466m123456p567s5m|NS1000","max_fans":[{"count":1,"name":"三色三步高","points":6}],"record_id":"TxVCM5mf","session_id":"RarhGLxm","timestamp_ms":1758286546693,"total_fan":14,"win_type":"tsumo"},{"hand_raw":"[234m,3]2233444p222s2p|SN0000","max_fans":[{"count":1,"name":"小于五","points":12}],"record_id":"YbWc1TPA","session_id":"hLPA55N1","timestamp_ms":1758549293003,"total_fan":19,"win_type":"ron"},{"hand_raw":"[456p,3]34566m456p56s7s|SW0100","max_fans":[{"count":1,"name":"三色三步高","points":6}],"record_id":"8jBidmGc","session_id":"hLPA55N1","timestamp_ms":1758549408131,"total_fan":16,"win_type":"ron"},{"hand_raw":"345m23499p12456s3s|WE0000","max_fans":[{"count":1,"name":"三色三步高","points":6}],"record_id":"vm7ysiHT","session_id":"hLPA55N1","timestamp_ms":1758549917148,"total_fan":14,"win_type":"ron"},{"hand_raw":"[456s,2][789p,1][567p,3]67pWW8p|NS0000","max_fans":[{"count":1,"name":"一色三步高","points":16}],"record_id":"vBwVkoXw","session_id":"hLPA55N1","timestamp_ms":1758550476441,"total_fan":18,"win_type":"ron"},{"hand_raw":"23455m234789p24s3s|NE0000","max_fans":[{"count":1,"name":"三色三同顺","points":8}],"record_id":"4ja9MgGq","session_id":"hLPA55N1","timestamp_ms":1758550698199,"total_fan":15,"win_type":"ron"},{"hand_raw":"345m567p456789sCC|SW0000","max_fans":[{"count":1,"name":"三色三步高","points":6}],"record_id":"gLSbYi1L","session_id":"fnDwd1Vu","timestamp_ms":1758632403758,"total_fan":11,"win_type":"ron"},{"hand_raw":"45668m345p11567s7m|WE1000","max_fans":[{"count":1,"name":"三色三步高","points":6}],"record_id":"pognK0Ji","session_id":"fnDwd1Vu","timestamp_ms":1758633021873,"total_fan":15,"win_type":"tsumo"},{"hand_raw":"[456m,2]12356m77p789s4m|NN0100","max_fans":[{"count":1,"name":"和绝张","points":4}],"record_id":"71jqNSdj","session_id":"fnDwd1Vu","timestamp_ms":1758634182623,"total_fan":9,"win_type":"ron"},{"hand_raw":"234m345p4666sWWW5s|WS1000","max_fans":[{"count":1,"name":"三色三步高","points":6}],"record_id":"9RR0ypR9","session_id":"XMXxUCca","timestamp_ms":1758716919916,"total_fan":18,"win_type":"tsumo"},{"hand_raw":"[789s,3][567s,2]55567p45s6s|EN1100","max_fans":[{"count":1,"name":"和绝张","points":4}],"record_id":"wEgJ7uZk","session_id":"Xy2hzmzP","timestamp_ms":1759413182898,"total_fan":11,"win_type":"tsumo"},{"hand_raw":"[EEEE,7][CCC,1]678m44p34s2s|SW0000","max_fans":[{"count":1,"name":"五门齐","points":6}],"record_id":"bFM6X7SF","session_id":"Xy2hzmzP","timestamp_ms":1759414516263,"total_fan":12,"win_type":"ron"},{"hand_raw":"345m23p12355567s4p|WE0000","max_fans":[{"count":1,"name":"三色三步高","points":6}],"record_id":"BvVYxk26","session_id":"Xy2hzmzP","timestamp_ms":1759415133306,"total_fan":11,"win_type":"ron"},{"hand_raw":"[888m,2][444s,3]66p22sFFF6p|EW0000","max_fans":[{"count":1,"name":"碰碰和","points":6}],"record_id":"iCXiZ4mw","session_id":"kvGf40MH","timestamp_ms":1760615443167,"total_fan":9,"win_type":"ron"},{"hand_raw":"[WWW,3][111s,2]2234567s2s|EN0000","max_fans":[{"count":1,"name":"混一色","points":6}],"record_id":"dMpSiHwk","session_id":"kvGf40MH","timestamp_ms":1760615837798,"total_fan":10,"win_type":"ron"},{"hand_raw":"[234m,2][EEE,3][234p,1]55p23s4s|SN1000","max_fans":[{"count":1,"name":"三色三同顺","points":8}],"record_id":"KjUxmhoH","session_id":"kvGf40MH","timestamp_ms":1760615998384,"total_fan":10,"win_type":"tsumo"},{"hand_raw":"[456m,3][567s,2][234s,3]66m67p8p|SS0000","max_fans":[{"count":1,"name":"三色三步高","points":6}],"record_id":"xQr985eG","session_id":"kvGf40MH","timestamp_ms":1760616234173,"total_fan":12,"win_type":"ron"},{"hand_raw":"[123p,2]23488m34789s5s|SE0000","max_fans":[{"count":1,"name":"三色三步高","points":6}],"record_id":"2xsFraG0","session_id":"kvGf40MH","timestamp_ms":1760616364806,"total_fan":9,"win_type":"ron"},{"hand_raw":"[123p,1][567p,3]67899m45p3p|WE0000","max_fans":[{"count":1,"name":"一色三连环","points":16}],"record_id":"1tRYH6AM","session_id":"kvGf40MH","timestamp_ms":1760616502410,"total_fan":22,"win_type":"ron"},{"hand_raw":"678m456p24567sSS3s|WS0000","max_fans":[{"count":1,"name":"三色三步高","points":6}],"record_id":"Q21rMDR8","session_id":"kvGf40MH","timestamp_ms":1760617025768,"total_fan":12,"win_type":"ron"},{"hand_raw":"[789m,2][345p,2]1145566p7p|EW0000","max_fans":[{"count":1,"name":"一色三步高","points":16}],"record_id":"AUkAnE6t","session_id":"UET06p4U","timestamp_ms":1760794073770,"total_fan":22,"win_type":"ron"},{"hand_raw":"[678m,2]33m567p12346s5s|ES0000","max_fans":[{"count":1,"name":"三色三步高","points":6}],"record_id":"LSsy6JRo","session_id":"UET06p4U","timestamp_ms":1760794224515,"total_fan":10,"win_type":"ron"},{"hand_raw":"[678p,2]567m11p45668s7s|WN1000","max_fans":[{"count":1,"name":"三色三步高","points":6}],"record_id":"nQW2vAqq","session_id":"UET06p4U","timestamp_ms":1760795073347,"total_fan":13,"win_type":"tsumo"},{"hand_raw":"[9999p,6]12345689mWW7m|NE0000","max_fans":[{"count":1,"name":"清龙","points":16}],"record_id":"jpZeirQC","session_id":"UET06p4U","timestamp_ms":1760796002369,"total_fan":22,"win_type":"ron"},{"hand_raw":"[345p,3]11m567sEEECCC|NN0000","max_fans":[{"count":1,"name":"五门齐","points":6}],"record_id":"iKUiCXA6","session_id":"UET06p4U","timestamp_ms":1760796173367,"total_fan":9,"win_type":"ron"},{"hand_raw":"[789s,3][123m,3]23466m56p4p|SW0000","max_fans":[{"count":1,"name":"花龙","points":8}],"record_id":"1jNrMM1d","session_id":"KLEWXenb","timestamp_ms":1760968610621,"total_fan":10,"win_type":"ron"},{"hand_raw":"[567p,3]67m11234456s8m|SE0000","max_fans":[{"count":1,"name":"三色三步高","points":6}],"record_id":"SjHgkHjU","session_id":"KLEWXenb","timestamp_ms":1760968786910,"total_fan":10,"win_type":"ron"},{"hand_raw":"[567m,3]34455p456sCC6p|EE0100","max_fans":[{"count":1,"name":"三色三步高","points":6}],"record_id":"ghpSTnD5","session_id":"Q09dAxYF","timestamp_ms":1761051710108,"total_fan":15,"win_type":"ron"},{"hand_raw":"13456789m22345p2m|EN0000","max_fans":[{"count":1,"name":"清龙","points":16}],"record_id":"fr0egmwF","session_id":"Q09dAxYF","timestamp_ms":1761051899765,"total_fan":25,"win_type":"ron"},{"hand_raw":"[999m,2][999p,2]789m88p88s8p|SW0000","max_fans":[{"count":1,"name":"全大","points":24}],"record_id":"CkgEy53P","session_id":"Q09dAxYF","timestamp_ms":1761052586901,"total_fan":32,"win_type":"ron"},{"hand_raw":"[567p,2]12345699m45s3s|EE0000","max_fans":[{"count":1,"name":"三色三步高","points":6}],"record_id":"FjWyw8iQ","session_id":"F6pB1UgG","timestamp_ms":1761139493159,"total_fan":9,"win_type":"ron"},{"hand_raw":"[123s,3]34m456789sEE2m|SE0000","max_fans":[{"count":1,"name":"清龙","points":16}],"record_id":"sqsdbR8C","session_id":"F6pB1UgG","timestamp_ms":1761140189131,"total_fan":17,"win_type":"ron"},{"hand_raw":"22m2244p88sEEWWCC|SW0000","max_fans":[{"count":1,"name":"七对","points":24}],"record_id":"2PKLnUpN","session_id":"F6pB1UgG","timestamp_ms":1761140374505,"total_fan":32,"win_type":"ron"},{"hand_raw":"234m33456p34579s8s|WN0000","max_fans":[{"count":1,"name":"三色三步高","points":6}],"record_id":"j3b1uUyA","session_id":"F6pB1UgG","timestamp_ms":1761140457229,"total_fan":12,"win_type":"ron"},{"hand_raw":"[123s,2][888m,1]123m23pFF1p|NW0000","max_fans":[{"count":1,"name":"三色三同顺","points":8}],"record_id":"7Zo5ghX0","session_id":"F6pB1UgG","timestamp_ms":1761141113831,"total_fan":10,"win_type":"ron"},{"hand_raw":"[123s,1][567m,1]12366m13p2p|NS0000","max_fans":[{"count":1,"name":"三色三同顺","points":8}],"record_id":"RhxnbQzd","session_id":"F6pB1UgG","timestamp_ms":1761141254572,"total_fan":11,"win_type":"ron"},{"hand_raw":"14499m334477sFF1m|EW0000","max_fans":[{"count":1,"name":"七对","points":24}],"record_id":"FMgQrcNp","session_id":"1tY4ziSt","timestamp_ms":1761221380379,"total_fan":25,"win_type":"ron"},{"hand_raw":"77m2244p225566sCC|WW0000","max_fans":[{"count":1,"name":"七对","points":24}],"record_id":"QX3fu9Hc","session_id":"1tY4ziSt","timestamp_ms":1761222430249,"total_fan":27,"win_type":"ron"},{"hand_raw":"77m6677p22339sFF9s|NE1000","max_fans":[{"count":1,"name":"七对","points":24}],"record_id":"aCoDvtpC","session_id":"1tY4ziSt","timestamp_ms":1761223971026,"total_fan":28,"win_type":"tsumo"},{"hand_raw":"[SSS,3][PPP,1]34578pFF6p|EW0000","max_fans":[{"count":1,"name":"混一色","points":6}],"record_id":"KQoc7Huf","session_id":"q6jxB6Up","timestamp_ms":1762260783659,"total_fan":11,"win_type":"ron"},{"hand_raw":"[123s,2]345999m2234p2p|SW0000","max_fans":[{"count":1,"name":"三色三步高","points":6}],"record_id":"gnAUVTx4","session_id":"q6jxB6Up","timestamp_ms":1762261895153,"total_fan":10,"win_type":"ron"},{"hand_raw":"[123m,3][234s,1][234m,2]1244p3p|WS1000","max_fans":[{"count":1,"name":"小于五","points":12}],"record_id":"eBL6SP9o","session_id":"q6jxB6Up","timestamp_ms":1762262380212,"total_fan":21,"win_type":"tsumo"},{"hand_raw":"[678p,3][789s,3][789m,3]2267m5m|NE1000","max_fans":[{"count":1,"name":"三色三步高","points":6}],"record_id":"PNAdPdX1","session_id":"q6jxB6Up","timestamp_ms":1762263359091,"total_fan":12,"win_type":"tsumo"},{"hand_raw":"[123s,3]123789m123p8s8s|EW0000","max_fans":[{"count":1,"name":"三色三同顺","points":8}],"record_id":"p4XeRUW6","session_id":"LzE7tcLJ","timestamp_ms":1764503063266,"total_fan":14,"win_type":"ron"},{"hand_raw":"[111s,1][444s,2]44488m23s4s|ES0100","max_fans":[{"count":1,"name":"和绝张","points":4}],"record_id":"4MrcDJ9w","session_id":"LzE7tcLJ","timestamp_ms":1764503199821,"total_fan":13,"win_type":"ron"},{"hand_raw":"[SSS,2]678m789p456sFF|SW0000","max_fans":[{"count":1,"name":"五门齐","points":6}],"record_id":"9WoEQZYy","session_id":"LzE7tcLJ","timestamp_ms":1764503888963,"total_fan":11,"win_type":"ron"},{"hand_raw":"[123m,1]567m11456p67s8s|WW0000","max_fans":[{"count":1,"name":"三色三步高","points":6}],"record_id":"cUtjeYp5","session_id":"LzE7tcLJ","timestamp_ms":1764504232093,"total_fan":9,"win_type":"ron"},{"hand_raw":"1222789m456p789s3m|WS0000","max_fans":[{"count":1,"name":"花龙","points":8}],"record_id":"gUWGXxDc","session_id":"LzE7tcLJ","timestamp_ms":1764504289310,"total_fan":14,"win_type":"ron"},{"hand_raw":"12399m12567789p3p|SW0000","max_fans":[{"count":1,"name":"门前清","points":2},{"count":1,"name":"平和","points":2}],"record_id":"fA2wRLEq","session_id":"F5KimPM3","timestamp_ms":1764937187304,"total_fan":8,"win_type":"ron"},{"hand_raw":"[678p,1]567m44p23446s5s|WE0000","max_fans":[{"count":1,"name":"三色三步高","points":6}],"record_id":"u8cLbgM7","session_id":"F5KimPM3","timestamp_ms":1764937583802,"total_fan":11,"win_type":"ron"},{"hand_raw":"[777p,3][8888m,1][444m,3]5559s9s|EN0000","max_fans":[{"count":1,"name":"碰碰和","points":6}],"record_id":"9aEkJ4Yh","session_id":"FvaMNV2z","timestamp_ms":1766753422413,"total_fan":13,"win_type":"ron"},{"hand_raw":"[SSS,3][CCCC,3][FFF,1]1234p4p|SN0000","max_fans":[{"count":1,"name":"混一色","points":6},{"count":1,"name":"双箭刻","points":6}],"record_id":"BobWgxwr","session_id":"FvaMNV2z","timestamp_ms":1766753628115,"total_fan":17,"win_type":"ron"},{"hand_raw":"[789s,3]67888p12456s3s|SE0000","max_fans":[{"count":1,"name":"清龙","points":16}],"record_id":"aayeGCwC","session_id":"FvaMNV2z","timestamp_ms":1766753992587,"total_fan":20,"win_type":"ron"},{"hand_raw":"444567m35p22456s4p|WE0000","max_fans":[{"count":1,"name":"三色三步高","points":6}],"record_id":"jQ5P1JDT","session_id":"FvaMNV2z","timestamp_ms":1766754069097,"total_fan":13,"win_type":"ron"},{"hand_raw":"12345679m33p567s8m|EE0000","max_fans":[{"count":1,"name":"清龙","points":16}],"record_id":"1Q6qxuEh","session_id":"Gzc3rC7D","timestamp_ms":1766755483083,"total_fan":21,"win_type":"ron"},{"hand_raw":"[123m,1]23445678p55s6p|WN0000","max_fans":[{"count":1,"name":"一色三连环","points":16}],"record_id":"3LPzNXnX","session_id":"Gzc3rC7D","timestamp_ms":1766756845314,"total_fan":19,"win_type":"ron"},{"hand_raw":"3567m678p344556s3m|WE0000","max_fans":[{"count":1,"name":"三色三步高","points":6}],"record_id":"iGk4HA9p","session_id":"Gzc3rC7D","timestamp_ms":1766757231955,"total_fan":15,"win_type":"ron"},{"hand_raw":"[999m,3]68m789p78889s7m|EN1000","max_fans":[{"count":1,"name":"大于五","points":12}],"record_id":"kdKdELkD","session_id":"9i3Jrmkn","timestamp_ms":1767096422208,"total_fan":18,"win_type":"tsumo"},{"hand_raw":"7799m4455p66sSSCC|ES0000","max_fans":[{"count":1,"name":"七对","points":24}],"record_id":"a60LQf3n","session_id":"9i3Jrmkn","timestamp_ms":1767096849426,"total_fan":31,"win_type":"ron"},{"hand_raw":"2455m567p123789s3m|WS1000","max_fans":[{"count":1,"name":"不求人","points":4}],"record_id":"vm4qGZ9e","session_id":"9i3Jrmkn","timestamp_ms":1767097937708,"total_fan":9,"win_type":"tsumo"},{"hand_raw":"[FFF,2][6666p,5][444p,3]33pNNN|WE1000","max_fans":[{"count":1,"name":"碰碰和","points":6},{"count":1,"name":"混一色","points":6}],"record_id":"Y3H35WQx","session_id":"9i3Jrmkn","timestamp_ms":1767098028917,"total_fan":18,"win_type":"tsumo"},{"hand_raw":"[456s,1]23457m23488p6m|ES0100","max_fans":[{"count":1,"name":"和绝张","points":4}],"record_id":"ecWujmSV","session_id":"XL6M8A3z","timestamp_ms":1767099279309,"total_fan":11,"win_type":"ron"},{"hand_raw":"[234p,1]456m22567p67s8s|WW0000","max_fans":[{"count":1,"name":"三色三步高","points":6}],"record_id":"uLnF3E9G","session_id":"XL6M8A3z","timestamp_ms":1767100364766,"total_fan":12,"win_type":"ron"}]}